timeset/__init__.py
timeset/timeinterval.py
timeset/timeset.py
pytimeset-0.1.dist-info/LICENSE
pytimeset-0.1.dist-info/METADATA
pytimeset-0.1.dist-info/WHEEL
pytimeset-0.1.dist-info/top_level.txt
pytimeset-0.1.dist-info/RECORD
