Metadata-Version: 2.1
Name: pytimeset
Version: 0.1
Summary: Defines sets and intervals to work with time, and provides arithmetic operations for them. 
Home-page: https://github.com/GFlorio/pytimeset
Author: Gabriel Florio
Author-email: gabriel@gabrielflorio.com
License: MIT
Platform: UNKNOWN
